{	"mc":{		"moban":{			"frameRate":8,			"labels":[{"name":"walk_4","frame":1,"end":8}],			"events":[],			"frames":[				{"res":"walk_40000","x":-131,"y":-222},				{"res":"walk_40001","x":-137,"y":-218},				{"res":"walk_40002","x":-139,"y":-213},				{"res":"walk_40003","x":-137,"y":-209},				{"res":"walk_40004","x":-131,"y":-212},				{"res":"walk_40005","x":-126,"y":-218}]		}	},		"res":{			"walk_40000":{"x":208,"y":244,"w":198,"h":236},			"walk_40001":{"x":2,"y":2,"w":202,"h":240},			"walk_40002":{"x":208,"y":2,"w":200,"h":238},			"walk_40003":{"x":2,"y":246,"w":195,"h":230},			"walk_40004":{"x":2,"y":716,"w":191,"h":229},			"walk_40005":{"x":2,"y":480,"w":190,"h":232}		}}