{	"mc":{		"moban":{			"frameRate":8,			"labels":[{"name":"openstand_7","frame":1,"end":8}],			"events":[],			"frames":[				{"res":"openstand_70000","x":-104,"y":-162},				{"res":"openstand_70001","x":-107,"y":-186},				{"res":"openstand_70002","x":-109,"y":-212},				{"res":"openstand_70003","x":-108,"y":-209},				{"res":"openstand_70004","x":-110,"y":-220},				{"res":"openstand_70005","x":-116,"y":-195}]		}	},		"res":{			"openstand_70000":{"x":124,"y":286,"w":110,"h":229},			"openstand_70001":{"x":367,"y":285,"w":111,"h":250},			"openstand_70002":{"x":124,"y":0,"w":121,"h":284},			"openstand_70003":{"x":247,"y":0,"w":118,"h":290},			"openstand_70004":{"x":0,"y":0,"w":122,"h":306},			"openstand_70005":{"x":367,"y":0,"w":119,"h":283}		}}