{	"mc":{		"moban":{			"frameRate":8,			"labels":[{"name":"ridewalk_0","frame":1,"end":8}],			"events":[],			"frames":[				{"res":"ridewalk_00000","x":-136,"y":-267},				{"res":"ridewalk_00001","x":-128,"y":-276},				{"res":"ridewalk_00002","x":-137,"y":-275},				{"res":"ridewalk_00003","x":-149,"y":-267},				{"res":"ridewalk_00004","x":-156,"y":-259},				{"res":"ridewalk_00005","x":-152,"y":-258}]		}	},		"res":{			"ridewalk_00000":{"x":603,"y":219,"w":287,"h":231},			"ridewalk_00001":{"x":291,"y":221,"w":274,"h":241},			"ridewalk_00002":{"x":0,"y":0,"w":289,"h":244},			"ridewalk_00003":{"x":603,"y":0,"w":307,"h":217},			"ridewalk_00004":{"x":567,"y":452,"w":318,"h":199},			"ridewalk_00005":{"x":291,"y":0,"w":310,"h":219}		}}