{"mc":{
	"moban":{
		"frameRate":8,
		"labels":[
			{"name":"stand_0","frame":1,"end":6}
			
			],
		"events":[
			
			],
		"frames":[
			
			{
			"res":"00000",
			"x":-193,
			"y":-251
			},
			{
			"res":"00001",
			"x":-195,
			"y":-251
			},
			{
			"res":"00002",
			"x":-193,
			"y":-250
			},
			{
			"res":"00003",
			"x":-194,
			"y":-250
			},
			{
			"res":"00004",
			"x":-196,
			"y":-249
			},
			{
			"res":"00005",
			"x":-196,
			"y":-251
			}
			]
}},
	"res":{
		"00000":{"x":669,"y":311,"w":330,"h":311},
		"00004":{"x":669,"y":0,"w":333,"h":309},
		"00005":{"x":0,"y":0,"w":333,"h":311},
		"00001":{"x":335,"y":0,"w":332,"h":311},
		"00002":{"x":0,"y":313,"w":330,"h":310},
		"00003":{"x":332,"y":313,"w":330,"h":310}
	}}