{	"mc":{		"moban":{			"frameRate":8,			"labels":[{"name":"walk_4","frame":1,"end":8}],			"events":[],			"frames":[				{"res":"walk_40000","x":-103,"y":-224},				{"res":"walk_40001","x":-69,"y":-212},				{"res":"walk_40002","x":-65,"y":-223},				{"res":"walk_40003","x":-82,"y":-225},				{"res":"walk_40004","x":-111,"y":-211},				{"res":"walk_40005","x":-120,"y":-223}]		}	},		"res":{			"walk_40000":{"x":0,"y":247,"w":181,"h":230},			"walk_40001":{"x":0,"y":479,"w":168,"h":232},			"walk_40002":{"x":190,"y":0,"w":170,"h":245},			"walk_40003":{"x":183,"y":474,"w":170,"h":233},			"walk_40004":{"x":183,"y":247,"w":184,"h":225},			"walk_40005":{"x":0,"y":0,"w":188,"h":245}		}}