{	"mc":{		"moban":{			"frameRate":8,			"labels":[{"name":"ridewalk_0","frame":1,"end":8}],			"events":[],			"frames":[				{"res":"ridewalk_00000","x":-58,"y":-159},				{"res":"ridewalk_00001","x":-56,"y":-152},				{"res":"ridewalk_00002","x":-58,"y":-151},				{"res":"ridewalk_00003","x":-63,"y":-153},				{"res":"ridewalk_00004","x":-65,"y":-160},				{"res":"ridewalk_00005","x":-62,"y":-164}]		}	},		"res":{			"ridewalk_00000":{"x":285,"y":116,"w":126,"h":115},			"ridewalk_00001":{"x":135,"y":127,"w":123,"h":106},			"ridewalk_00002":{"x":1,"y":125,"w":130,"h":106},			"ridewalk_00003":{"x":285,"y":1,"w":141,"h":111},			"ridewalk_00004":{"x":1,"y":1,"w":142,"h":120},			"ridewalk_00005":{"x":147,"y":1,"w":134,"h":122}		}}