{	"mc":{		"moban":{			"frameRate":8,			"labels":[{"name":"ridestand_5","frame":1,"end":8}],			"events":[],			"frames":[				{"res":"ridestand_50000","x":-23,"y":-107},				{"res":"ridestand_50001","x":-24,"y":-107},				{"res":"ridestand_50002","x":-25,"y":-107},				{"res":"ridestand_50003","x":-25,"y":-109},				{"res":"ridestand_50004","x":-24,"y":-107},				{"res":"ridestand_50005","x":-24,"y":-106}]		}	},		"res":{			"ridestand_50000":{"x":397,"y":141,"w":98,"h":136},			"ridestand_50001":{"x":397,"y":0,"w":98,"h":139},			"ridestand_50002":{"x":298,"y":0,"w":97,"h":141},			"ridestand_50003":{"x":0,"y":0,"w":96,"h":146},			"ridestand_50004":{"x":98,"y":0,"w":97,"h":143},			"ridestand_50005":{"x":197,"y":0,"w":99,"h":140}		}}