{	"mc":{		"moban":{			"frameRate":8,			"labels":[{"name":"ridestand_7","frame":1,"end":8}],			"events":[],			"frames":[				{"res":"ridestand_70000","x":-136,"y":-123},				{"res":"ridestand_70001","x":-138,"y":-123},				{"res":"ridestand_70002","x":-127,"y":-123},				{"res":"ridestand_70003","x":-135,"y":-122},				{"res":"ridestand_70004","x":-138,"y":-122},				{"res":"ridestand_70005","x":-140,"y":-123}]		}	},		"res":{			"ridestand_70000":{"x":129,"y":157,"w":126,"h":152},			"ridestand_70001":{"x":0,"y":156,"w":127,"h":154},			"ridestand_70002":{"x":329,"y":154,"w":150,"h":155},			"ridestand_70003":{"x":167,"y":0,"w":160,"h":155},			"ridestand_70004":{"x":329,"y":0,"w":159,"h":152},			"ridestand_70005":{"x":0,"y":0,"w":165,"h":154}		}}