{	"mc":{		"moban":{			"frameRate":8,			"labels":[{"name":"walk_5","frame":1,"end":8}],			"events":[],			"frames":[				{"res":"walk_50000","x":-47,"y":-116},				{"res":"walk_50001","x":-34,"y":-110},				{"res":"walk_50002","x":-32,"y":-113},				{"res":"walk_50003","x":-44,"y":-110},				{"res":"walk_50004","x":-28,"y":-116},				{"res":"walk_50005","x":-37,"y":-124}]		}	},		"res":{			"walk_50000":{"x":0,"y":0,"w":116,"h":152},			"walk_50001":{"x":0,"y":302,"w":103,"h":147},			"walk_50002":{"x":114,"y":161,"w":103,"h":149},			"walk_50003":{"x":0,"y":154,"w":112,"h":146},			"walk_50004":{"x":105,"y":312,"w":96,"h":152},			"walk_50005":{"x":118,"y":0,"w":109,"h":159}		}}