{	"mc":{		"moban":{			"frameRate":8,			"labels":[{"name":"jump2_0","frame":1,"end":8}],			"events":[],			"frames":[				{"res":"jump2_00000","x":-52,"y":-93},				{"res":"jump2_00001","x":-52,"y":-121},				{"res":"jump2_00002","x":-52,"y":-168},				{"res":"jump2_00003","x":-52,"y":-105}]		}	},		"res":{			"jump2_00000":{"x":0,"y":130,"w":104,"h":120},			"jump2_00001":{"x":104,"y":130,"w":116,"h":93},			"jump2_00002":{"x":0,"y":0,"w":107,"h":130},			"jump2_00003":{"x":107,"y":0,"w":115,"h":88}		}}