{	"mc":{		"moban":{			"frameRate":8,			"labels":[{"name":"walk_6","frame":1,"end":8}],			"events":[],			"frames":[				{"res":"walk_60000","x":-74,"y":-94},				{"res":"walk_60001","x":-72,"y":-96},				{"res":"walk_60002","x":-69,"y":-99},				{"res":"walk_60003","x":-72,"y":-94},				{"res":"walk_60004","x":-72,"y":-96},				{"res":"walk_60005","x":-67,"y":-100}]		}	},		"res":{			"walk_60000":{"x":1,"y":1,"w":153,"h":115},			"walk_60001":{"x":310,"y":118,"w":141,"h":117},			"walk_60002":{"x":1,"y":120,"w":142,"h":116},			"walk_60003":{"x":147,"y":120,"w":139,"h":112},			"walk_60004":{"x":310,"y":1,"w":150,"h":113},			"walk_60005":{"x":158,"y":1,"w":148,"h":115}		}}