{	"mc":{		"moban":{			"frameRate":8,			"labels":[{"name":"walk_4","frame":1,"end":8}],			"events":[],			"frames":[				{"res":"walk_40000","x":-147,"y":-223},				{"res":"walk_40001","x":-132,"y":-224},				{"res":"walk_40002","x":-139,"y":-222},				{"res":"walk_40003","x":-153,"y":-215},				{"res":"walk_40004","x":-159,"y":-215},				{"res":"walk_40005","x":-157,"y":-222}]		}	},		"res":{			"walk_40000":{"x":0,"y":242,"w":283,"h":211},			"walk_40001":{"x":285,"y":256,"w":260,"h":213},			"walk_40002":{"x":303,"y":0,"w":273,"h":254},			"walk_40003":{"x":578,"y":0,"w":291,"h":238},			"walk_40004":{"x":0,"y":0,"w":301,"h":240},			"walk_40005":{"x":578,"y":240,"w":302,"h":223}		}}