{	"mc":{		"moban":{			"frameRate":8,			"labels":[{"name":"walk_7","frame":1,"end":8}],			"events":[],			"frames":[				{"res":"walk_70000","x":-98,"y":-136},				{"res":"walk_70001","x":-103,"y":-133},				{"res":"walk_70002","x":-76,"y":-132},				{"res":"walk_70003","x":-66,"y":-136},				{"res":"walk_70004","x":-60,"y":-137},				{"res":"walk_70005","x":-75,"y":-134}]		}	},		"res":{			"walk_70000":{"x":2,"y":2,"w":169,"h":151},			"walk_70001":{"x":175,"y":2,"w":169,"h":143},			"walk_70002":{"x":175,"y":149,"w":127,"h":132},			"walk_70003":{"x":306,"y":283,"w":114,"h":139},			"walk_70004":{"x":348,"y":143,"w":134,"h":136},			"walk_70005":{"x":348,"y":2,"w":156,"h":137}		}}