{"mc":{
	"moban":{
		"frameRate":12,
		"labels":[
			{"name":"jm_0","frame":1,"end":9}
			
			],
		"events":[
			
			],
		"frames":[
			
			{
			"res":"00000",
			"x":-47,
			"y":-45
			},
			{
			"res":"00001",
			"x":-53,
			"y":-50
			},
			{
			"res":"00002",
			"x":-59,
			"y":-57
			},
			{
			"res":"00003",
			"x":-63,
			"y":-60
			},
			{
			"res":"00004",
			"x":-59,
			"y":-57
			},
			{
			"res":"00005",
			"x":-57,
			"y":-54
			},
			{
			"res":"00006",
			"x":-57,
			"y":-50
			},
			{
			"res":"00007",
			"x":-60,
			"y":-49
			},
			{
			"res":"00008",
			"x":-63,
			"y":-39
			}
			]
}},
	"res":{
		"00007":{"x":126,"y":120,"w":111,"h":102},
		"00008":{"x":0,"y":126,"w":117,"h":86},
		"00000":{"x":0,"y":214,"w":94,"h":94},
		"00004":{"x":246,"y":0,"w":118,"h":118},
		"00006":{"x":366,"y":114,"w":109,"h":104},
		"00003":{"x":0,"y":0,"w":124,"h":124},
		"00001":{"x":239,"y":120,"w":105,"h":104},
		"00005":{"x":366,"y":0,"w":113,"h":112},
		"00002":{"x":126,"y":0,"w":118,"h":118}
	}}