{	"mc":{		"moban":{			"frameRate":8,			"labels":[{"name":"walk_7","frame":1,"end":8}],			"events":[],			"frames":[				{"res":"walk_70000","x":-146,"y":-247},				{"res":"walk_70001","x":-145,"y":-254},				{"res":"walk_70002","x":-150,"y":-256},				{"res":"walk_70003","x":-148,"y":-248},				{"res":"walk_70004","x":-148,"y":-243},				{"res":"walk_70005","x":-148,"y":-243}]		}	},		"res":{			"walk_70000":{"x":225,"y":514,"w":228,"h":256},			"walk_70001":{"x":0,"y":513,"w":223,"h":264},			"walk_70002":{"x":248,"y":0,"w":239,"h":261},			"walk_70003":{"x":0,"y":0,"w":246,"h":254},			"walk_70004":{"x":0,"y":263,"w":251,"h":248},			"walk_70005":{"x":253,"y":263,"w":244,"h":249}		}}