{	"mc":{		"moban":{			"frameRate":8,			"labels":[{"name":"walk_0","frame":1,"end":8}],			"events":[],			"frames":[				{"res":"walk_00000","x":-62,"y":-95},				{"res":"walk_00001","x":-48,"y":-113},				{"res":"walk_00002","x":-50,"y":-110},				{"res":"walk_00003","x":-45,"y":-96},				{"res":"walk_00004","x":-59,"y":-111},				{"res":"walk_00005","x":-66,"y":-103}]		}	},		"res":{			"walk_00000":{"x":277,"y":1,"w":135,"h":86},			"walk_00001":{"x":1,"y":1,"w":136,"h":124},			"walk_00002":{"x":139,"y":1,"w":136,"h":112},			"walk_00003":{"x":279,"y":89,"w":132,"h":85},			"walk_00004":{"x":1,"y":127,"w":137,"h":123},			"walk_00005":{"x":140,"y":115,"w":137,"h":107}		}}