{	"mc":{		"moban":{			"frameRate":8,			"labels":[{"name":"openstand_7","frame":1,"end":8}],			"events":[],			"frames":[				{"res":"openstand_70000","x":-51,"y":-125},				{"res":"openstand_70001","x":-51,"y":-126},				{"res":"openstand_70002","x":-48,"y":-128},				{"res":"openstand_70003","x":-46,"y":-129},				{"res":"openstand_70004","x":-45,"y":-129},				{"res":"openstand_70005","x":-47,"y":-126}]		}	},		"res":{			"openstand_70000":{"x":1,"y":1,"w":103,"h":123},			"openstand_70001":{"x":108,"y":1,"w":103,"h":123},			"openstand_70002":{"x":1,"y":128,"w":98,"h":123},			"openstand_70003":{"x":1,"y":255,"w":96,"h":123},			"openstand_70004":{"x":101,"y":255,"w":95,"h":124},			"openstand_70005":{"x":103,"y":128,"w":97,"h":123}		}}