{	"mc":{		"moban":{			"frameRate":8,			"labels":[{"name":"stand_6","frame":1,"end":8}],			"events":[],			"frames":[				{"res":"stand_60000","x":-130,"y":-264},				{"res":"stand_60001","x":-110,"y":-241},				{"res":"stand_60002","x":-140,"y":-195},				{"res":"stand_60003","x":-82,"y":-132}]		}	},		"res":{			"stand_60000":{"x":0,"y":0,"w":343,"h":274},			"stand_60001":{"x":345,"y":0,"w":288,"h":251},			"stand_60002":{"x":635,"y":0,"w":309,"h":205},			"stand_60003":{"x":635,"y":207,"w":182,"h":142}		}}