{	"mc":{		"moban":{			"frameRate":8,			"labels":[{"name":"ridestand_4","frame":1,"end":8}],			"events":[],			"frames":[				{"res":"ridestand_40000","x":-164,"y":-191},				{"res":"ridestand_40001","x":-163,"y":-190},				{"res":"ridestand_40002","x":-163,"y":-190},				{"res":"ridestand_40003","x":-163,"y":-190},				{"res":"ridestand_40004","x":-163,"y":-192},				{"res":"ridestand_40005","x":-163,"y":-194}]		}	},		"res":{			"ridestand_40000":{"x":312,"y":0,"w":314,"h":161},			"ridestand_40001":{"x":628,"y":0,"w":314,"h":160},			"ridestand_40002":{"x":628,"y":162,"w":312,"h":160},			"ridestand_40003":{"x":624,"y":324,"w":311,"h":159},			"ridestand_40004":{"x":312,"y":163,"w":310,"h":161},			"ridestand_40005":{"x":0,"y":0,"w":310,"h":164}		}}