{	"mc":{		"moban":{			"frameRate":24,			"labels":[{"name":"stand_0","frame":1,"end":20}],			"events":[],			"frames":[				{"res":"attack1_60000","x":-256,"y":-282},				{"res":"attack1_60001","x":-256,"y":-282},				{"res":"attack1_60002","x":-256,"y":-282},				{"res":"attack1_60003","x":-91,"y":-134},				{"res":"attack1_60004","x":-82,"y":-128},				{"res":"attack1_60005","x":-64,"y":-136},				{"res":"attack1_60006","x":2,"y":-125},				{"res":"attack1_60007","x":15,"y":-124},				{"res":"attack1_60008","x":16,"y":-124},				{"res":"attack1_60009","x":33,"y":-121},				{"res":"attack1_60010","x":37,"y":-117},				{"res":"attack1_60011","x":53,"y":-112}]		}	},		"res":{			"attack1_60000":{"x":1011,"y":0,"w":1,"h":1},			"attack1_60001":{"x":1014,"y":0,"w":1,"h":1},			"attack1_60002":{"x":1017,"y":0,"w":1,"h":1},			"attack1_60003":{"x":0,"y":0,"w":347,"h":191},			"attack1_60004":{"x":349,"y":0,"w":338,"h":186},			"attack1_60005":{"x":689,"y":0,"w":320,"h":181},			"attack1_60006":{"x":689,"y":183,"w":254,"h":164},			"attack1_60007":{"x":349,"y":188,"w":240,"h":162},			"attack1_60008":{"x":0,"y":193,"w":236,"h":161},			"attack1_60009":{"x":591,"y":349,"w":212,"h":156},			"attack1_60010":{"x":805,"y":349,"w":188,"h":143},			"attack1_60011":{"x":238,"y":352,"w":162,"h":137}		}}