{"mc":{
	"moban":{
		"frameRate":8,
		"labels":[
			{"name":"stand_0","frame":1,"end":18}
			
			],
		"events":[
			
			],
		"frames":[
			
			{
			"res":"stand_00",
			"x":-4,
			"y":-369
			},
			{
			"res":"stand_01",
			"x":-5,
			"y":-349
			},
			{
			"res":"stand_02",
			"x":-59,
			"y":-369
			},
			{
			"res":"stand_03",
			"x":-59,
			"y":-322
			},
			{
			"res":"stand_04",
			"x":-109,
			"y":-357
			},
			{
			"res":"stand_05",
			"x":-108,
			"y":-307
			},
			{
			"res":"stand_06",
			"x":-108,
			"y":-369
			},
			{
			"res":"stand_07",
			"x":-108,
			"y":-283
			},
			{
			"res":"stand_08",
			"x":-110,
			"y":-136
			},
			{
			"res":"stand_09",
			"x":-112,
			"y":-142
			},
			{
			"res":"stand_010",
			"x":-113,
			"y":-134
			},
			{
			"res":"stand_011",
			"x":-113,
			"y":-119
			},
			{
			"res":"stand_012",
			"x":-99,
			"y":-121
			},
			{
			"res":"stand_013",
			"x":-99,
			"y":-120
			},
			{
			"res":"stand_014",
			"x":-71,
			"y":-126
			},
			{
			"res":"stand_015",
			"x":-69,
			"y":-103
			},
			{
			"res":"stand_016",
			"x":-69,
			"y":-87
			},
			{
			"res":"stand_017",
			"x":-22,
			"y":-86
			}
			]
}},
	"res":{
		"stand_06":{"x":0,"y":0,"w":194,"h":437},
		"stand_013":{"x":224,"y":618,"w":212,"h":189},
		"stand_017":{"x":421,"y":362,"w":128,"h":110},
		"stand_07":{"x":590,"y":0,"w":196,"h":351},
		"stand_08":{"x":737,"y":596,"w":219,"h":204},
		"stand_014":{"x":649,"y":802,"w":184,"h":190},
		"stand_012":{"x":438,"y":689,"w":209,"h":191},
		"stand_015":{"x":0,"y":439,"w":182,"h":167},
		"stand_09":{"x":737,"y":383,"w":223,"h":211},
		"stand_02":{"x":788,"y":0,"w":144,"h":381},
		"stand_01":{"x":934,"y":0,"w":50,"h":266},
		"stand_016":{"x":835,"y":802,"w":175,"h":151},
		"stand_04":{"x":196,"y":0,"w":196,"h":410},
		"stand_05":{"x":394,"y":0,"w":194,"h":360},
		"stand_010":{"x":196,"y":412,"w":223,"h":204},
		"stand_011":{"x":0,"y":618,"w":222,"h":189},
		"stand_03":{"x":590,"y":353,"w":145,"h":334},
		"stand_00":{"x":962,"y":268,"w":50,"h":206}
	}}