{	"mc":{		"moban":{			"frameRate":8,			"labels":[{"name":"stand_0","frame":1,"end":8}],			"events":[],			"frames":[				{"res":"stand_00000","x":-101,"y":-86},				{"res":"stand_00001","x":-102,"y":-87},				{"res":"stand_00002","x":-103,"y":-87},				{"res":"stand_00003","x":-103,"y":-86},				{"res":"stand_00004","x":-103,"y":-86},				{"res":"stand_00005","x":-102,"y":-86}]		}	},		"res":{			"stand_00000":{"x":239,"y":0,"w":116,"h":142},			"stand_00001":{"x":0,"y":0,"w":117,"h":142},			"stand_00002":{"x":119,"y":0,"w":118,"h":140},			"stand_00003":{"x":119,"y":142,"w":118,"h":138},			"stand_00004":{"x":357,"y":143,"w":117,"h":139},			"stand_00005":{"x":357,"y":0,"w":116,"h":141}		}}