{	"mc":{		"moban":{			"frameRate":8,			"labels":[{"name":"walk_6","frame":1,"end":8}],			"events":[],			"frames":[				{"res":"walk_60000","x":-69,"y":-107},				{"res":"walk_60001","x":-50,"y":-109},				{"res":"walk_60002","x":-47,"y":-112},				{"res":"walk_60003","x":-69,"y":-107},				{"res":"walk_60004","x":-50,"y":-110},				{"res":"walk_60005","x":-48,"y":-113}]		}	},		"res":{			"walk_60000":{"x":1,"y":1,"w":143,"h":113},			"walk_60001":{"x":1,"y":118,"w":126,"h":118},			"walk_60002":{"x":295,"y":1,"w":127,"h":119},			"walk_60003":{"x":148,"y":1,"w":143,"h":112},			"walk_60004":{"x":280,"y":124,"w":128,"h":113},			"walk_60005":{"x":148,"y":117,"w":128,"h":117}		}}