{	"mc":{		"moban":{			"frameRate":8,			"labels":[{"name":"openstand_6","frame":1,"end":8}],			"events":[],			"frames":[				{"res":"openstand_60000","x":-14,"y":-71},				{"res":"openstand_60001","x":-14,"y":-72},				{"res":"openstand_60002","x":-15,"y":-73},				{"res":"openstand_60003","x":-16,"y":-73},				{"res":"openstand_60004","x":-16,"y":-72},				{"res":"openstand_60005","x":-15,"y":-71}]		}	},		"res":{			"openstand_60000":{"x":1,"y":66,"w":136,"h":63},			"openstand_60001":{"x":1,"y":131,"w":136,"h":62},			"openstand_60002":{"x":283,"y":1,"w":136,"h":60},			"openstand_60003":{"x":1,"y":195,"w":140,"h":60},			"openstand_60004":{"x":142,"y":1,"w":139,"h":61},			"openstand_60005":{"x":1,"y":1,"w":139,"h":63}		}}