{	"mc":{		"moban":{			"frameRate":8,			"labels":[{"name":"walk_6","frame":1,"end":8}],			"events":[],			"frames":[				{"res":"walk_60000","x":-105,"y":-104},				{"res":"walk_60001","x":-104,"y":-102},				{"res":"walk_60002","x":-100,"y":-107},				{"res":"walk_60003","x":-100,"y":-104},				{"res":"walk_60004","x":-100,"y":-102},				{"res":"walk_60005","x":-102,"y":-107}]		}	},		"res":{			"walk_60000":{"x":199,"y":1,"w":194,"h":131},			"walk_60001":{"x":1,"y":140,"w":193,"h":127},			"walk_60002":{"x":199,"y":136,"w":193,"h":130},			"walk_60003":{"x":1,"y":271,"w":189,"h":128},			"walk_60004":{"x":198,"y":270,"w":189,"h":129},			"walk_60005":{"x":1,"y":1,"w":194,"h":135}		}}