{	"mc":{		"moban":{			"frameRate":8,			"labels":[{"name":"stand_4","frame":1,"end":8}],			"events":[],			"frames":[				{"res":"stand_40000","x":-41,"y":-96},				{"res":"stand_40001","x":-42,"y":-89},				{"res":"stand_40002","x":-44,"y":-85},				{"res":"stand_40003","x":-41,"y":-85},				{"res":"stand_40004","x":-39,"y":-85},				{"res":"stand_40005","x":-31,"y":-85}]		}	},		"res":{			"stand_40000":{"x":0,"y":0,"w":151,"h":117},			"stand_40001":{"x":153,"y":0,"w":156,"h":108},			"stand_40002":{"x":311,"y":0,"w":159,"h":103},			"stand_40003":{"x":311,"y":105,"w":159,"h":103},			"stand_40004":{"x":153,"y":110,"w":153,"h":106},			"stand_40005":{"x":0,"y":119,"w":143,"h":107}		}}