{	"mc":{		"moban":{			"frameRate":8,			"labels":[{"name":"walk_5","frame":1,"end":8}],			"events":[],			"frames":[				{"res":"walk_50000","x":-50,"y":-111},				{"res":"walk_50001","x":-36,"y":-112},				{"res":"walk_50002","x":-37,"y":-118},				{"res":"walk_50003","x":-50,"y":-111},				{"res":"walk_50004","x":-38,"y":-112},				{"res":"walk_50005","x":-40,"y":-117}]		}	},		"res":{			"walk_50000":{"x":331,"y":0,"w":110,"h":126},			"walk_50001":{"x":108,"y":129,"w":100,"h":128},			"walk_50002":{"x":0,"y":0,"w":106,"h":137},			"walk_50003":{"x":108,"y":0,"w":114,"h":127},			"walk_50004":{"x":331,"y":128,"w":100,"h":132},			"walk_50005":{"x":224,"y":0,"w":105,"h":132}		}}