{"mc":{
	"moban":{
		"frameRate":12,
		"labels":[
			{"name":"stand_0","frame":1,"end":6}
			
			],
		"events":[
			
			],
		"frames":[
			
			{
			"res":"00000",
			"x":-87,
			"y":-137
			},
			{
			"res":"00001",
			"x":-86,
			"y":-137
			},
			{
			"res":"00002",
			"x":-86,
			"y":-137
			},
			{
			"res":"00003",
			"x":-86,
			"y":-137
			},
			{
			"res":"00004",
			"x":-86,
			"y":-138
			},
			{
			"res":"00005",
			"x":-87,
			"y":-137
			}
			]
}},
	"res":{
		"00002":{"x":485,"y":0,"w":240,"h":227},
		"00000":{"x":0,"y":0,"w":241,"h":228},
		"00001":{"x":243,"y":0,"w":240,"h":228},
		"00004":{"x":727,"y":228,"w":240,"h":226},
		"00005":{"x":727,"y":0,"w":241,"h":226},
		"00003":{"x":485,"y":229,"w":240,"h":226}
	}}